pyboneco/__init__.py
pyboneco/advertising_data.py
pyboneco/auth.py
pyboneco/client.py
pyboneco/constants.py
pyboneco/device.py
pyboneco/device_info.py
pyboneco/device_state.py
pyboneco/enums.py
pyboneco/py.typed
pyboneco/utils.py
pyboneco-0.4.1.dist-info/METADATA
pyboneco-0.4.1.dist-info/WHEEL
pyboneco-0.4.1.dist-info/licenses/LICENSE
pyboneco-0.4.1.dist-info/RECORD
